CHANGES.txt
COPYRIGHT.txt
LICENSE.txt
README.txt
TODO.txt
bootstrap.py
buildout.cfg
setup.py
ztk-versions-1.0.1.cfg
src/cipher/__init__.py
src/cipher.configstore.egg-info/PKG-INFO
src/cipher.configstore.egg-info/SOURCES.txt
src/cipher.configstore.egg-info/dependency_links.txt
src/cipher.configstore.egg-info/not-zip-safe
src/cipher.configstore.egg-info/requires.txt
src/cipher.configstore.egg-info/top_level.txt
src/cipher/configstore/__init__.py
src/cipher/configstore/configstore.py
src/cipher/configstore/configstore.txt
src/cipher/configstore/interfaces.py
src/cipher/configstore/tests.py