Metadata-Version: 1.1
Name: cipher.configstore
Version: 1.3.2
Summary: UNKNOWN
Home-page: http://pypi.python.org/pypi/cipher.configstore/
Author: Zope Foundation and Contributors
Author-email: zope-dev@zope.org
License: ZPL 2.1
Keywords: CipherHealth configuration storage configparser
Platform: UNKNOWN
Classifier: Development Status :: 4 - Beta
Classifier: Environment :: Web Environment
Classifier: Intended Audience :: Developers
Classifier: Programming Language :: Python
Classifier: Natural Language :: English
Classifier: Operating System :: OS Independent
Classifier: Topic :: Internet :: WWW/HTTP
Classifier: Framework :: Zope3
